mesalab/__init__.py
mesalab/cli.py
mesalab/version.py
mesalab/analyzis/__init__.py
mesalab/analyzis/data_reader.py
mesalab/analyzis/grid_analyzer.py
mesalab/analyzis/mesa_analyzer.py
mesalab/bluelooptools/__init__.py
mesalab/bluelooptools/blue_loop_analyzer.py
mesalab/bluelooptools/blue_loop_cmd_plotter.py
mesalab/gyretools/__init__.py
mesalab/gyretools/gyre_modules.py
mesalab/io/__init__.py
mesalab/io/config_parser.py
mesalab/io/config_paths.py
mesalab/io/inlist_parser.py
mesalab/io/output_manager.py
mesalab/plotting/__init__.py
mesalab/plotting/all_hrd_plotter.py
mesalab/plotting/heatmap_generator.py
mesalab/plotting/mesa_plotter.py
mesalab/rsptools/__init__.py
mesalab/rsptools/rsp_inlist_generator.py
mesalab/rsptools/rsp_runner.py
mesalab-2.1.0.dist-info/licenses/LICENSE
mesalab-2.1.0.dist-info/METADATA
mesalab-2.1.0.dist-info/WHEEL
mesalab-2.1.0.dist-info/entry_points.txt
mesalab-2.1.0.dist-info/top_level.txt
mesalab-2.1.0.dist-info/RECORD
